{
  "display": {
    "icon": {
      "item": "minecraft:melon"
    },
    "title": {
      "translate": "advancements.melon_block_avencement.title"
    },
    "description": {
      "translate": "advancements.melon_block_avencement.descr"
    },
    "frame": "goal",
    "show_toast": true,
    "announce_to_chat": true,
    "hidden": false
  },
  "criteria": {
    "melon_block_avencement": {
      "trigger": "minecraft:inventory_changed",
      "conditions": {
        "items": [
          {
            "items": [
              "minecraft:melon"
            ],
            "count": {
              "min": 1,
              "max": 1
            }
          }
        ]
      }
    }
  },
  "rewards": {
    "experience": 1
  },
  "parent": "the_legende_of_luma:melon_avecement"
}